dingsound/__init__.py
dingsound/functions.py
dingsound/test.py
dingsound-0.0.5.dist-info/METADATA
dingsound-0.0.5.dist-info/WHEEL
dingsound-0.0.5.dist-info/top_level.txt
dingsound-0.0.5.dist-info/RECORD
